_mysql.so
_mysql_exceptions.py
MySQL_python_vincent-1.2.5.dist-info/DESCRIPTION.rst
MySQL_python_vincent-1.2.5.dist-info/METADATA
MySQL_python_vincent-1.2.5.dist-info/RECORD
MySQL_python_vincent-1.2.5.dist-info/WHEEL
MySQL_python_vincent-1.2.5.dist-info/metadata.json
MySQL_python_vincent-1.2.5.dist-info/top_level.txt
MySQLdb/__init__.py
MySQLdb/connections.py
MySQLdb/converters.py
MySQLdb/cursors.py
MySQLdb/release.py
MySQLdb/times.py
MySQLdb/constants/CLIENT.py
MySQLdb/constants/CR.py
MySQLdb/constants/ER.py
MySQLdb/constants/FIELD_TYPE.py
MySQLdb/constants/FLAG.py
MySQLdb/constants/REFRESH.py
MySQLdb/constants/__init__.py
