Metadata-Version: 2.0
Name: MySQL-python-vincent
Version: 1.2.5
Summary: Python interface to MySQL
Home-page: https://github.com/farcepest/MySQLdb1
Author: vin
Author-email: deded@gamil.com
License: GPL
Platform: ALL
Classifier: Development Status :: 5 - Production/Stable
Classifier: Environment :: Other Environment
Classifier: License :: OSI Approved :: GNU General Public License (GPL)
Classifier: Operating System :: MacOS :: MacOS X
Classifier: Operating System :: Microsoft :: Windows :: Windows NT/2000
Classifier: Operating System :: OS Independent
Classifier: Operating System :: POSIX
Classifier: Operating System :: POSIX :: Linux
Classifier: Operating System :: Unix
Classifier: Programming Language :: C
Classifier: Programming Language :: Python
Classifier: Topic :: Database
Classifier: Topic :: Database :: Database Engines/Servers
